py_evalexpr-1.1.0.dist-info/METADATA
py_evalexpr-1.1.0.dist-info/WHEEL
py_evalexpr-1.1.0.dist-info/licenses/LICENSE
py_evalexpr.libs/libgcc_s-98a1ef30.so.1
py_evalexpr/__init__.py
py_evalexpr/base_context.py
py_evalexpr/exceptions.py
py_evalexpr/functions.py
py_evalexpr/immutable_context.py
py_evalexpr/mutable_context.py
py_evalexpr/natives.cpython-312-x86_64-linux-musl.so
py_evalexpr/natives/context.pyi
py_evalexpr/natives/evaluate.pyi
py_evalexpr/natives/evaluate_with_context.pyi
py_evalexpr/natives/evaluate_with_context_mut.pyi
py_evalexpr/natives/result.pyi
py_evalexpr/quickeval.py
py_evalexpr/stateless_context.py
py_evalexpr/variables.py
py_evalexpr-1.1.0.dist-info/RECORD
