Metadata-Version: 2.4
Name: py_evalexpr
Version: 1.1.0
Classifier: Programming Language :: Rust
Classifier: Programming Language :: Python :: Implementation :: CPython
Classifier: Programming Language :: Python :: Implementation :: PyPy
License-File: LICENSE
Summary: Python bindings for evalexpr Rust crate for safe expression evaluation
Author-email: Benjamin Kiiskila <benjaminckiiskila@gmail.com>
License: MIT
Requires-Python: >=3.11
